deckcards/__init__.py
deckcards/card.py
deckcards/deck.py
deckcards/error.py
deckcards/logger.py
deckcards/examples/__init__.py
deckcards/examples/blackjack.py
deckofcards/__init__.py
deckofcards/card.py
deckofcards/deck.py
deckofcards/error.py
deckofcards/logger.py
deckofcards/examples/__init__.py
deckofcards/examples/blackjack.py
deckcards-1.0.1.dist-info/LICENSE
deckcards-1.0.1.dist-info/METADATA
deckcards-1.0.1.dist-info/WHEEL
deckcards-1.0.1.dist-info/top_level.txt
deckcards-1.0.1.dist-info/RECORD
