Metadata-Version: 2.1
Name: deckcards
Version: 1.0.1
Summary: Framework for creating or playing card games
Home-page: https://github.com/bessavagner/deckcards
Author: Vagner Bessa
Author-email: bessavagner@gmail.com
Project-URL: Documentation, https://github.com/bessavagner/deckcards
Keywords: card,game,python
Classifier: Development Status :: 5 - Production/Stable
Classifier: Intended Audience :: Developers
Classifier: Topic :: Games/Entertainment :: Board Games
Classifier: Programming Language :: Python :: 3
Classifier: Programming Language :: Python :: 3.8
Classifier: Programming Language :: Python :: 3.9
Classifier: Programming Language :: Python :: 3.10
Classifier: Programming Language :: Python :: 3 :: Only
Classifier: License :: OSI Approved :: MIT License
Classifier: Operating System :: OS Independent
Requires-Python: >=3.8
License-File: LICENSE
Provides-Extra: dev
Requires-Dist: check-manifest ; extra == 'dev'
